test/graph_test.py
traph/__init__.py
traph/algorithms.py
traph/graph_constructor.py
traph/main.py
traph/ui/__init__.py
traph/ui/shapes.py
traph/ui/ui.py
traph-0.0.2.dist-info/LICENSE
traph-0.0.2.dist-info/METADATA
traph-0.0.2.dist-info/WHEEL
traph-0.0.2.dist-info/entry_points.txt
traph-0.0.2.dist-info/top_level.txt
traph-0.0.2.dist-info/RECORD
