Metadata-Version: 2.1
Name: traph
Version: 0.0.2
Summary: The terminal graph visualiser no one asked for
License: MIT License
Project-URL: Repository, https://github.com/1MaxKoval/traph
Keywords: graph,terminal,game,visualiser
Classifier: Topic :: Games/Entertainment
Classifier: Topic :: Terminals
Requires-Python: >=3.8
License-File: LICENSE
Requires-Dist: blessed
Requires-Dist: bresenham
